psy_maps/__init__.py
psy_maps/_version.py
psy_maps/boxes.py
psy_maps/plotters.py
psy_maps/plugin.py
psy_maps/widgets/__init__.py
psy_maps-1.5.0.dist-info/CC-BY-4.0.txt
psy_maps-1.5.0.dist-info/CC0-1.0.txt
psy_maps-1.5.0.dist-info/LGPL-3.0-only.txt
psy_maps-1.5.0.dist-info/METADATA
psy_maps-1.5.0.dist-info/WHEEL
psy_maps-1.5.0.dist-info/entry_points.txt
psy_maps-1.5.0.dist-info/top_level.txt
psy_maps-1.5.0.dist-info/RECORD
